{
  "current_phase": "2_TRACEABILITY",
  "previous_phases": [
    {
      "phase": "0_INIT",
      "completed": "2025-09-24T23:52:00Z",
      "milestones": [
        "Project structure created",
        "Docker environment configured",
        "Base dependencies installed",
        "Database schema initialized"
      ]
    },
    {
      "phase": "1_CORE_REQUIREMENTS",
      "completed": "2025-09-25T09:47:00Z",
      "milestones": [
        "Requirements CRUD API working",
        "Unique ID generation system",
        "Basic versioning implemented",
        "Audit logging active"
      ]
    }
  ],
  "completed_milestones": [
    "Bidirectional linking works",
    "Suspect link flagging implemented",
    "Traceability matrix renders",
    "Coverage gap detection active"
  ],
  "active_agents": {
    "Agent-Links": "completed",
    "Agent-Matrix": "completed",
    "Agent-Analytics": "completed",
    "Agent-Test": "completed"
  },
  "test_results": {
    "bidirectional_linking": "passed",
    "link_retrieval": "passed",
    "suspect_flagging": "passed",
    "traceability_matrix": "passed",
    "coverage_analysis": "passed"
  },
  "phase_start": "2025-09-25T09:48:00Z",
  "phase_completed": "2025-09-25T10:14:00Z",
  "last_updated": "2025-09-25T10:14:00Z"
}